easy_start_wecom/__init__.py
easy_start_wecom/server/__init__.py
easy_start_wecom/webhook/__init__.py
easy_start_wecom-0.2.0.dist-info/licenses/LICENSE
easy_start_wecom-0.2.0.dist-info/METADATA
easy_start_wecom-0.2.0.dist-info/WHEEL
easy_start_wecom-0.2.0.dist-info/top_level.txt
easy_start_wecom-0.2.0.dist-info/RECORD
