Metadata-Version: 2.4
Name: easy-start-wecom
Version: 0.2.0
Summary: 一个用于企业微信(WeCom)集成的Python包，提供简洁易用的API接口，支持同步和异步操作，帮助开发者快速实现企业微信相关功能。
Home-page: https://gitee.com/guolei19850528/easy_start_wecom
Author: guolei
Author-email: 174000902@qq.com
Classifier: Programming Language :: Python :: 3
Classifier: License :: OSI Approved :: MIT License
Classifier: Operating System :: OS Independent
Requires-Python: >=3.6
License-File: LICENSE
Requires-Dist: httpx
Requires-Dist: diskcache
Requires-Dist: redis
Requires-Dist: jsonschema
Dynamic: author
Dynamic: author-email
Dynamic: classifier
Dynamic: description
Dynamic: description-content-type
Dynamic: home-page
Dynamic: license-file
Dynamic: requires-dist
Dynamic: requires-python
Dynamic: summary
